LICENSE
MANIFEST.in
README.rst
setup.py
tox.ini
lemon_publications.egg-info/PKG-INFO
lemon_publications.egg-info/SOURCES.txt
lemon_publications.egg-info/dependency_links.txt
lemon_publications.egg-info/top_level.txt
publications/__init__.py
publications/admin.py
publications/feeds.py
publications/managers.py
publications/models.py
publications/querysets.py
publications/tests.py
publications/views.py
publications/locale/ru/LC_MESSAGES/django.mo
publications/locale/ru/LC_MESSAGES/django.po
tests/__init__.py
tests/runtests.sh
tests/settings.py